hexlib/HexTwin.py
hexlib/Hexdump.py
hexlib/PerfMon.py
hexlib/TestFileCreator.py
hexlib/__init__.py
hexlib-2.0.3.dist-info/LICENSE.md
hexlib-2.0.3.dist-info/METADATA
hexlib-2.0.3.dist-info/WHEEL
hexlib-2.0.3.dist-info/top_level.txt
hexlib-2.0.3.dist-info/RECORD
