Metadata-Version: 2.1
Name: hexlib
Version: 2.0.3
Summary: Basic tools to read, filter, format and display hex values
Home-page: https://github.com/5f0ne/hexlib
Author: 5f0
License: MIT
Classifier: Operating System :: OS Independent 
Classifier: Programming Language :: Python :: 3 
Classifier: License :: OSI Approved :: MIT License 
License-File: LICENSE.md
